genepattern/__init__.py
genepattern/authwidget.py
genepattern/demo_mode.py
genepattern/display.py
genepattern/jobwidget.py
genepattern/jupyter_extensions.py
genepattern/local_widgets.py
genepattern/remote_widgets.py
genepattern/sessions.py
genepattern/shim.py
genepattern/taskwidget.py
genepattern/utils.py
genepattern/static/index.js
genepattern/static/resources/background.png
genepattern/static/resources/genepattern.authentication.js
genepattern/static/resources/genepattern.css
genepattern/static/resources/genepattern.job.js
genepattern/static/resources/genepattern.js
genepattern/static/resources/genepattern.modulebundler.js
genepattern/static/resources/genepattern.navigation.js
genepattern/static/resources/genepattern.task.js
genepattern/static/resources/gp-icon.png
genepattern/static/resources/gp-logo.png
genepattern/static/resources/loading.gif
genepattern_notebook-25.7.data/data/share/jupyter/nbtools/genepattern.json
genepattern_notebook-25.7.dist-info/LICENSE.txt
genepattern_notebook-25.7.dist-info/METADATA
genepattern_notebook-25.7.dist-info/WHEEL
genepattern_notebook-25.7.dist-info/top_level.txt
genepattern_notebook-25.7.dist-info/RECORD
