Metadata-Version: 2.1
Name: genepattern-notebook
Version: 25.7
Summary: GenePattern Notebook extension for JupyterLab
Home-page: https://github.com/genepattern/genepattern-notebook
Download-URL: https://github.com/genepattern/genepattern-notebook/archive/25.07.tar.gz
Author: Thorin Tabor
Author-email: tmtabor@cloud.ucsd.edu
License: BSD
Keywords: genepattern,genomics,bioinformatics,ipython,jupyter
Classifier: Development Status :: 5 - Production/Stable
Classifier: Intended Audience :: Science/Research
Classifier: Intended Audience :: Developers
Classifier: Topic :: Scientific/Engineering :: Bio-Informatics
Classifier: License :: OSI Approved :: BSD License
Classifier: Programming Language :: Python :: 3.6
Classifier: Programming Language :: Python :: 3.7
Classifier: Programming Language :: Python :: 3.8
Classifier: Programming Language :: Python :: 3.9
Classifier: Framework :: Jupyter
License-File: LICENSE.txt
Requires-Dist: genepattern-python (>=1.4.2)
Requires-Dist: nbtools (>=23.4)
Requires-Dist: notebook (>=5.0.0)
Requires-Dist: ipywidgets (>=7.0.0)
Requires-Dist: pandas
